UserAgentFilter/__init__.py
UserAgentFilter/tester.py
UserAgentFilter/utils.py
UserAgentFilter-1.0.0.dist-info/LICENSE
UserAgentFilter-1.0.0.dist-info/METADATA
UserAgentFilter-1.0.0.dist-info/WHEEL
UserAgentFilter-1.0.0.dist-info/top_level.txt
UserAgentFilter-1.0.0.dist-info/RECORD
